pdferli/README.MD
pdferli/__init__.py
pdferli/requirements.txt
pdferli/thirdparty.json
pdferli-0.11.dist-info/LICENSE.rst
pdferli-0.11.dist-info/METADATA
pdferli-0.11.dist-info/WHEEL
pdferli-0.11.dist-info/top_level.txt
pdferli-0.11.dist-info/RECORD
