Metadata-Version: 2.1
Name: pdferli
Version: 0.11
Summary: Convert PDFs into pandas DataFrames, remove restrictions, put/crack PDF passwords
Home-page: https://github.com/hansalemaos/pdferli
Author: Johannes Fischer
Author-email: aulasparticularesdealemaosp@gmail.com
License: MIT
Keywords: pdf,parsing,passwords
Classifier: Development Status :: 4 - Beta
Classifier: Programming Language :: Python :: 3 :: Only
Classifier: Programming Language :: Python :: 3.10
Classifier: Topic :: Software Development :: Libraries :: Python Modules
Classifier: Topic :: Utilities
License-File: LICENSE.rst
Requires-Dist: a-pandas-ex-less-memory-more-speed
Requires-Dist: flatten-any-dict-iterable-or-whatsoever
Requires-Dist: pandas
Requires-Dist: pdfminer.six
Requires-Dist: pikepdf
Requires-Dist: touchtouch
